aio_pool/__init__.py
aio_pool/pool.py
aio_pool-0.2.0.dist-info/LICENSE
aio_pool-0.2.0.dist-info/WHEEL
aio_pool-0.2.0.dist-info/METADATA
aio_pool-0.2.0.dist-info/RECORD
