Metadata-Version: 2.1
Name: aio-pool
Version: 0.2.0
Summary: Extending Python's process pool to support async functions.
Home-page: https://github.com/Itayazolay/aio-pool
License: Apache-2.0
Author: Itay Azolay
Author-email: itayazolay@gmail.com
Requires-Python: >=3.6,<4.0
Classifier: Development Status :: 4 - Beta
Classifier: Framework :: AsyncIO
Classifier: Intended Audience :: Developers
Classifier: License :: OSI Approved :: Apache Software License
Classifier: Programming Language :: Python :: 3
Classifier: Programming Language :: Python :: 3.6
Classifier: Programming Language :: Python :: 3.7
Classifier: Programming Language :: Python :: 3.8
Classifier: Programming Language :: Python :: 3.9
Classifier: Topic :: Software Development :: Libraries
Classifier: Topic :: Software Development :: Libraries :: Python Modules
Project-URL: Repository, https://github.com/Itayazolay/aio-pool
